df3dPostProcessing/__init__.py
df3dPostProcessing/df3dPostProcessing.py
df3dPostProcessing/utils/__init__.py
df3dPostProcessing/utils/utils_alignment.py
df3dPostProcessing/utils/utils_angles.py
df3dPostProcessing/utils/utils_ball_info.py
df3dPostProcessing/utils/utils_outliers.py
df3dPostProcessing/utils/utils_plots.py
df3dpostprocessing-1.1.0.dist-info/licenses/LICENSE
df3dpostprocessing-1.1.0.dist-info/METADATA
df3dpostprocessing-1.1.0.dist-info/WHEEL
df3dpostprocessing-1.1.0.dist-info/top_level.txt
df3dpostprocessing-1.1.0.dist-info/RECORD
