Metadata-Version: 2.4
Name: df3dPostProcessing
Version: 1.1.0
Summary: Postprocessing functions for DeepFly3D results
Author-email: Victor Lobato <victor.lobatorios@epfl.ch>
License: MIT License
Project-URL: Repository, https://github.com/NeLy-EPFL/df3dPostProcessing
Keywords: kinematic analysis,Drosophila,DeepFly3D
Classifier: Programming Language :: Python :: 3
Classifier: License :: OSI Approved :: MIT License
Classifier: Operating System :: OS Independent
License-File: LICENSE
Requires-Dist: numpy
Requires-Dist: scipy
Requires-Dist: matplotlib
Requires-Dist: opencv-python-headless
Requires-Dist: opencv-contrib-python-headless
Requires-Dist: seaborn
Requires-Dist: scikit-learn
Requires-Dist: pandas
Requires-Dist: ikpy
Requires-Dist: nely-pyba
Dynamic: license-file
